applet3-0.1.dev1.dist-info/licenses/LICENSE
appletree/__init__.py
appletree/_version.py
appletree/_widget.py
appletree/molmosam2.py
appletree/napari.yaml
appletree/sam2.1_hiera_b+.yaml
appletree/utils.py
appletree/_tests/__init__.py
appletree/_tests/test_widget.py
appletree/sam2/__init__.py
appletree/sam2/automatic_mask_generator.py
appletree/sam2/benchmark.py
appletree/sam2/build_sam.py
appletree/sam2/sam2_hiera_b+.yaml
appletree/sam2/sam2_hiera_l.yaml
appletree/sam2/sam2_hiera_s.yaml
appletree/sam2/sam2_hiera_t.yaml
appletree/sam2/sam2_image_predictor.py
appletree/sam2/sam2_video_predictor.py
appletree/sam2/sam2_video_predictor_legacy.py
appletree/sam2/configs/sam2/sam2_hiera_b+.yaml
appletree/sam2/configs/sam2/sam2_hiera_l.yaml
appletree/sam2/configs/sam2/sam2_hiera_s.yaml
appletree/sam2/configs/sam2/sam2_hiera_t.yaml
appletree/sam2/modeling/__init__.py
appletree/sam2/modeling/memory_attention.py
appletree/sam2/modeling/memory_encoder.py
appletree/sam2/modeling/position_encoding.py
appletree/sam2/modeling/sam2_base.py
appletree/sam2/modeling/sam2_utils.py
appletree/sam2/modeling/backbones/__init__.py
appletree/sam2/modeling/backbones/hieradet.py
appletree/sam2/modeling/backbones/image_encoder.py
appletree/sam2/modeling/backbones/utils.py
appletree/sam2/modeling/sam/__init__.py
appletree/sam2/modeling/sam/mask_decoder.py
appletree/sam2/modeling/sam/prompt_encoder.py
appletree/sam2/modeling/sam/transformer.py
appletree/sam2/utils/__init__.py
appletree/sam2/utils/amg.py
appletree/sam2/utils/misc.py
appletree/sam2/utils/transforms.py
applet3-0.1.dev1.dist-info/METADATA
applet3-0.1.dev1.dist-info/WHEEL
applet3-0.1.dev1.dist-info/entry_points.txt
applet3-0.1.dev1.dist-info/top_level.txt
applet3-0.1.dev1.dist-info/RECORD
