Metadata-Version: 2.4
Name: AppleT3
Version: 0.1.dev1
Summary: Apple tree segmentation for young apple tree
Author: Herearii Metuarea
Author-email: herearii.metuarea@univ-angers.fr
License: 
Project-URL: Bug Tracker, https://github.com/hereariim/appletree/issues
Project-URL: Documentation, https://github.com/hereariim/appletree#README.md
Project-URL: Source Code, https://github.com/hereariim/appletree
Project-URL: User Support, https://github.com/hereariim/appletree/issues
Classifier: Development Status :: 2 - Pre-Alpha
Classifier: Framework :: napari
Classifier: Intended Audience :: Developers
Classifier: License :: OSI Approved :: BSD License
Classifier: Operating System :: OS Independent
Classifier: Programming Language :: Python
Classifier: Programming Language :: Python :: 3
Classifier: Programming Language :: Python :: 3 :: Only
Classifier: Programming Language :: Python :: 3.10
Classifier: Programming Language :: Python :: 3.11
Classifier: Programming Language :: Python :: 3.12
Classifier: Programming Language :: Python :: 3.13
Classifier: Topic :: Scientific/Engineering :: Image Processing
Requires-Python: ==3.10.16
License-File: LICENSE
Requires-Dist: numpy
Requires-Dist: magicgui
Requires-Dist: qtpy
Requires-Dist: scikit-image
Requires-Dist: torch>=2.5.1
Requires-Dist: torchvision>=0.20.1
Requires-Dist: numpy>=1.24.4
Requires-Dist: tqdm>=4.66.1
Requires-Dist: hydra-core>=1.3.2
Requires-Dist: iopath>=0.1.10
Requires-Dist: pillow>=9.4.0
Requires-Dist: supervision==0.25.1
Requires-Dist: transformers==4.51.3
Requires-Dist: einops==0.8.1
Requires-Dist: tensorflow==2.19.0
Requires-Dist: accelerate==1.6.0
Provides-Extra: testing
Requires-Dist: tox; extra == "testing"
Requires-Dist: pytest; extra == "testing"
Requires-Dist: pytest-cov; extra == "testing"
Requires-Dist: pytest-qt; extra == "testing"
Requires-Dist: napari; extra == "testing"
Requires-Dist: pyqt5; extra == "testing"
Dynamic: license-file
